<?xml version="1.0" encoding="utf-8" ?>
<dwsync>
<file name="10.jpg" local="130825572112079811" remote="130848654000000000" testing="0" />
<file name="11.jpg" local="130825572112139840" remote="130848654000000000" testing="0" />
<file name="12.jpg" local="130825572112210185" remote="130848654000000000" testing="0" />
<file name="13.jpg" local="130825572112269970" remote="130848654000000000" testing="0" />
<file name="14.jpg" local="130825572112350055" remote="130848654000000000" testing="0" />
<file name="6.jpg" local="130825572112410113" remote="130848654000000000" testing="0" />
<file name="7.jpg" local="130825572112470163" remote="130848654000000000" testing="0" />
<file name="8.jpg" local="130825572112540226" remote="130848654600000000" testing="0" />
<file name="9.jpg" local="130825572112610285" remote="130848654600000000" testing="0" />
<file name="back-blue.jpg" local="130825572112650595" remote="130848654600000000" testing="0" />
<file name="back-green.jpg" local="130825572112690361" remote="130848654600000000" testing="0" />
<file name="back-orange.png" local="130825572113001064" remote="130848654600000000" testing="0" />
<file name="blueish.jpg" local="130825572113140767" remote="130848654600000000" testing="0" />
<file name="landscape.jpg" local="130825572113190816" remote="130848654600000000" testing="0" />
</dwsync>